odoo/addons/l10n_ro_stock/README.rst
odoo/addons/l10n_ro_stock/__init__.py
odoo/addons/l10n_ro_stock/__manifest__.py
odoo/addons/l10n_ro_stock/i18n/l10n_ro_stock.pot
odoo/addons/l10n_ro_stock/models/__init__.py
odoo/addons/l10n_ro_stock/models/stock_location.py
odoo/addons/l10n_ro_stock/models/stock_warehouse.py
odoo/addons/l10n_ro_stock/static/description/icon.png
odoo/addons/l10n_ro_stock/tests/__init__.py
odoo/addons/l10n_ro_stock/tests/test_stock_warehouse_creation.py
odoo/addons/l10n_ro_stock/views/stock_location_view.xml
odoo/addons/l10n_ro_stock/views/stock_warehouse_view.xml
odoo11_addon_l10n_ro_stock-11.0.1.0.0.99.dev3.dist-info/METADATA
odoo11_addon_l10n_ro_stock-11.0.1.0.0.99.dev3.dist-info/WHEEL
odoo11_addon_l10n_ro_stock-11.0.1.0.0.99.dev3.dist-info/top_level.txt
odoo11_addon_l10n_ro_stock-11.0.1.0.0.99.dev3.dist-info/RECORD
